streamlit_globe/__init__.py
streamlit_globe/frontend/build/asset-manifest.json
streamlit_globe/frontend/build/bootstrap.min.css
streamlit_globe/frontend/build/index.html
streamlit_globe/frontend/build/precache-manifest.a7428282e9436bfe7c980b13fc84917a.js
streamlit_globe/frontend/build/service-worker.js
streamlit_globe/frontend/build/static/js/2.70ab07e1.chunk.js
streamlit_globe/frontend/build/static/js/2.70ab07e1.chunk.js.LICENSE.txt
streamlit_globe/frontend/build/static/js/2.70ab07e1.chunk.js.map
streamlit_globe/frontend/build/static/js/main.b270d566.chunk.js
streamlit_globe/frontend/build/static/js/main.b270d566.chunk.js.map
streamlit_globe/frontend/build/static/js/runtime-main.b2da421e.js
streamlit_globe/frontend/build/static/js/runtime-main.b2da421e.js.map
streamlit_globe/frontend/build/static/media/earth-day2.8ec81bb4.jpg
streamlit_globe/frontend/build/static/media/earth-night.5350543d.jpg
streamlit_globe/frontend/build/static/media/night-sky.1701d635.png
streamlit_globe-0.2.1.dist-info/LICENSE
streamlit_globe-0.2.1.dist-info/METADATA
streamlit_globe-0.2.1.dist-info/WHEEL
streamlit_globe-0.2.1.dist-info/top_level.txt
streamlit_globe-0.2.1.dist-info/RECORD
