Metadata-Version: 2.1
Name: streamlit-globe
Version: 0.2.1
Summary: An wrapper of the threeJS globe to display points and labels on a globe.
Home-page: https://github.com/padmalcom/streamlit_globe
Author: Jonas Freiknecht
Author-email: j.freiknecht@googlemail.com
License: UNKNOWN
Platform: UNKNOWN
Requires-Python: >=3.6
License-File: LICENSE
Requires-Dist: streamlit (>=0.63)
